<?xml version="1.0" encoding="UTF-8" standalone="no"?>
<interaction xmlns="http://opends.eu/drivingtask/interaction" xmlns:xsi="http://www.w3.org/2001/XMLSchema-instance" xsi:schemaLocation="http://opends.eu/drivingtask/interaction ../../Schema/interaction.xsd">
	<activities>
		<activity id="Start_startRM" ref="">
			<action delay="0.0" id="startReactionMeasurement" repeat="1"/>
		</activity>
		<activity id="Start_startRecording" ref="">
			<action delay="0.0" id="startRecording" repeat="4">
				<parameter name="track" value="1"/>
			</action>
		</activity>
		<activity id="End_stopRecording" ref="">
			<action delay="0.0" id="stopRecording" repeat="4"/>
		</activity>
		<activity id="End_pauseSimulation" ref="">
			<action delay="0.0" id="pauseSimulation" repeat="4">
				<parameter name="duration" value="0"/>
			</action>
		</activity>
		<activity id="BLC_Test_Block0_Trial0_Trigger0_makeVisible_BLC_Test_Block0_Trial0_ContainerElements" ref="">
			<action delay="0.0" id="manipulateObject" repeat="1">
				<parameter name="visible" value="true"/>
				<parameter name="id" value="BLC_Test_Block0_Trial0_ContainerElement0"/>
			</action>
			<action delay="0.0" id="manipulateObject" repeat="1">
				<parameter name="visible" value="true"/>
				<parameter name="id" value="BLC_Test_Block0_Trial0_ContainerElement1"/>
			</action>
			<action delay="0.0" id="manipulateObject" repeat="1">
				<parameter name="visible" value="true"/>
				<parameter name="id" value="BLC_Test_Block0_Trial0_ContainerElement2"/>
			</action>
		</activity>
		<activity id="BLC_Test_Block0_Trial0_Trigger0_setupBrakeLaneChangeReactionTimer" ref="">
			<action delay="0.0" id="setupLaneChangeReactionTimer" repeat="1">
				<parameter name="minSteeringAngle" value="0"/>
				<parameter name="targetLane" value="2"/>
				<parameter name="startLane" value="1"/>
				<parameter name="taskCompletionAfterDistance" value="117"/>
				<parameter name="taskCompletionAfterTime" value="7000"/>
				<parameter name="timerID" value="timer1"/>
				<parameter name="allowBreak" value="true"/>
				<parameter name="successSound" value="good"/>
				<parameter name="congruenceClass" value="LaneChange"/>
				<parameter name="holdLaneFor" value="2000"/>
				<parameter name="failSound" value="fail"/>
			</action>
		</activity>
		<activity id="BLC_Test_Block0_Trial0_Trigger0_Sound_Stimulus" ref="">
			<action delay="0.0" id="playSound" repeat="1">
				<parameter name="soundID" value="left1"/>
			</action>
		</activity>
		<activity id="BLC_Test_Block0_Trial1_Trigger0_makeVisible_BLC_Test_Block0_Trial1_ContainerElements" ref="">
			<action delay="0.0" id="manipulateObject" repeat="1">
				<parameter name="visible" value="true"/>
				<parameter name="id" value="BLC_Test_Block0_Trial1_ContainerElement0"/>
			</action>
			<action delay="0.0" id="manipulateObject" repeat="1">
				<parameter name="visible" value="true"/>
				<parameter name="id" value="BLC_Test_Block0_Trial1_ContainerElement1"/>
			</action>
			<action delay="0.0" id="manipulateObject" repeat="1">
				<parameter name="visible" value="true"/>
				<parameter name="id" value="BLC_Test_Block0_Trial1_ContainerElement2"/>
			</action>
		</activity>
		<activity id="BLC_Test_Block0_Trial1_Trigger0_setupBrakeLaneChangeReactionTimer" ref="">
			<action delay="0.0" id="setupLaneChangeReactionTimer" repeat="1">
				<parameter name="minSteeringAngle" value="0"/>
				<parameter name="targetLane" value="1"/>
				<parameter name="startLane" value="2"/>
				<parameter name="taskCompletionAfterDistance" value="117"/>
				<parameter name="taskCompletionAfterTime" value="7000"/>
				<parameter name="timerID" value="timer1"/>
				<parameter name="allowBreak" value="true"/>
				<parameter name="successSound" value="good"/>
				<parameter name="congruenceClass" value="LaneChange"/>
				<parameter name="holdLaneFor" value="2000"/>
				<parameter name="failSound" value="fail"/>
			</action>
		</activity>
		<activity id="BLC_Test_Block0_Trial1_Trigger0_Sound_Stimulus" ref="">
			<action delay="0.0" id="playSound" repeat="1">
				<parameter name="soundID" value="right1"/>
			</action>
		</activity>
		<activity id="BLC_Test_Block0_Trial2_Trigger0_makeVisible_BLC_Test_Block0_Trial2_ContainerElements" ref="">
			<action delay="0.0" id="manipulateObject" repeat="1">
				<parameter name="visible" value="true"/>
				<parameter name="id" value="BLC_Test_Block0_Trial2_ContainerElement0"/>
			</action>
			<action delay="0.0" id="manipulateObject" repeat="1">
				<parameter name="visible" value="true"/>
				<parameter name="id" value="BLC_Test_Block0_Trial2_ContainerElement1"/>
			</action>
			<action delay="0.0" id="manipulateObject" repeat="1">
				<parameter name="visible" value="true"/>
				<parameter name="id" value="BLC_Test_Block0_Trial2_ContainerElement2"/>
			</action>
		</activity>
		<activity id="BLC_Test_Block0_Trial2_Trigger0_setupBrakeLaneChangeReactionTimer" ref="">
			<action delay="0.0" id="setupLaneChangeReactionTimer" repeat="1">
				<parameter name="minSteeringAngle" value="0"/>
				<parameter name="targetLane" value="0"/>
				<parameter name="startLane" value="1"/>
				<parameter name="taskCompletionAfterDistance" value="117"/>
				<parameter name="taskCompletionAfterTime" value="7000"/>
				<parameter name="timerID" value="timer1"/>
				<parameter name="allowBreak" value="true"/>
				<parameter name="successSound" value="good"/>
				<parameter name="congruenceClass" value="LaneChange"/>
				<parameter name="holdLaneFor" value="2000"/>
				<parameter name="failSound" value="fail"/>
			</action>
		</activity>
		<activity id="BLC_Test_Block0_Trial2_Trigger0_Sound_Stimulus" ref="">
			<action delay="0.0" id="playSound" repeat="1">
				<parameter name="soundID" value="right1"/>
			</action>
		</activity>
		<activity id="BLC_Test_Block0_Trial3_Trigger0_makeVisible_BLC_Test_Block0_Trial3_ContainerElements" ref="">
			<action delay="0.0" id="manipulateObject" repeat="1">
				<parameter name="visible" value="true"/>
				<parameter name="id" value="BLC_Test_Block0_Trial3_ContainerElement0"/>
			</action>
			<action delay="0.0" id="manipulateObject" repeat="1">
				<parameter name="visible" value="true"/>
				<parameter name="id" value="BLC_Test_Block0_Trial3_ContainerElement1"/>
			</action>
			<action delay="0.0" id="manipulateObject" repeat="1">
				<parameter name="visible" value="true"/>
				<parameter name="id" value="BLC_Test_Block0_Trial3_ContainerElement2"/>
			</action>
		</activity>
		<activity id="BLC_Test_Block0_Trial3_Trigger0_setupBrakeLaneChangeReactionTimer" ref="">
			<action delay="0.0" id="setupLaneChangeReactionTimer" repeat="1">
				<parameter name="minSteeringAngle" value="0"/>
				<parameter name="targetLane" value="2"/>
				<parameter name="startLane" value="0"/>
				<parameter name="taskCompletionAfterDistance" value="117"/>
				<parameter name="taskCompletionAfterTime" value="7000"/>
				<parameter name="timerID" value="timer1"/>
				<parameter name="allowBreak" value="true"/>
				<parameter name="successSound" value="good"/>
				<parameter name="congruenceClass" value="LaneChange"/>
				<parameter name="holdLaneFor" value="2000"/>
				<parameter name="failSound" value="fail"/>
			</action>
		</activity>
		<activity id="BLC_Test_Block0_Trial3_Trigger0_Sound_Stimulus" ref="">
			<action delay="0.0" id="playSound" repeat="1">
				<parameter name="soundID" value="left2"/>
			</action>
		</activity>
		<activity id="BLC_Test_Block0_Trial4_Trigger0_makeVisible_BLC_Test_Block0_Trial4_ContainerElements" ref="">
			<action delay="0.0" id="manipulateObject" repeat="1">
				<parameter name="visible" value="true"/>
				<parameter name="id" value="BLC_Test_Block0_Trial4_ContainerElement0"/>
			</action>
			<action delay="0.0" id="manipulateObject" repeat="1">
				<parameter name="visible" value="true"/>
				<parameter name="id" value="BLC_Test_Block0_Trial4_ContainerElement1"/>
			</action>
			<action delay="0.0" id="manipulateObject" repeat="1">
				<parameter name="visible" value="true"/>
				<parameter name="id" value="BLC_Test_Block0_Trial4_ContainerElement2"/>
			</action>
		</activity>
		<activity id="BLC_Test_Block0_Trial4_Trigger0_setupBrakeLaneChangeReactionTimer" ref="">
			<action delay="0.0" id="setupLaneChangeReactionTimer" repeat="1">
				<parameter name="minSteeringAngle" value="0"/>
				<parameter name="targetLane" value="0"/>
				<parameter name="startLane" value="2"/>
				<parameter name="taskCompletionAfterDistance" value="117"/>
				<parameter name="taskCompletionAfterTime" value="7000"/>
				<parameter name="timerID" value="timer1"/>
				<parameter name="allowBreak" value="true"/>
				<parameter name="successSound" value="good"/>
				<parameter name="congruenceClass" value="LaneChange"/>
				<parameter name="holdLaneFor" value="2000"/>
				<parameter name="failSound" value="fail"/>
			</action>
		</activity>
		<activity id="BLC_Test_Block0_Trial4_Trigger0_Sound_Stimulus" ref="">
			<action delay="0.0" id="playSound" repeat="1">
				<parameter name="soundID" value="right2"/>
			</action>
		</activity>
		<activity id="BLC_Test_Block0_Trial5_Trigger0_makeVisible_BLC_Test_Block0_Trial5_ContainerElements" ref="">
			<action delay="0.0" id="manipulateObject" repeat="1">
				<parameter name="visible" value="true"/>
				<parameter name="id" value="BLC_Test_Block0_Trial5_ContainerElement0"/>
			</action>
			<action delay="0.0" id="manipulateObject" repeat="1">
				<parameter name="visible" value="true"/>
				<parameter name="id" value="BLC_Test_Block0_Trial5_ContainerElement1"/>
			</action>
			<action delay="0.0" id="manipulateObject" repeat="1">
				<parameter name="visible" value="true"/>
				<parameter name="id" value="BLC_Test_Block0_Trial5_ContainerElement2"/>
			</action>
		</activity>
		<activity id="BLC_Test_Block0_Trial5_Trigger0_setupBrakeLaneChangeReactionTimer" ref="">
			<action delay="0.0" id="setupLaneChangeReactionTimer" repeat="1">
				<parameter name="minSteeringAngle" value="0"/>
				<parameter name="targetLane" value="2"/>
				<parameter name="startLane" value="0"/>
				<parameter name="taskCompletionAfterDistance" value="117"/>
				<parameter name="taskCompletionAfterTime" value="7000"/>
				<parameter name="timerID" value="timer1"/>
				<parameter name="allowBreak" value="true"/>
				<parameter name="successSound" value="good"/>
				<parameter name="congruenceClass" value="LaneChange"/>
				<parameter name="holdLaneFor" value="2000"/>
				<parameter name="failSound" value="fail"/>
			</action>
		</activity>
		<activity id="BLC_Test_Block0_Trial5_Trigger0_Sound_Stimulus" ref="">
			<action delay="0.0" id="playSound" repeat="1">
				<parameter name="soundID" value="left2"/>
			</action>
		</activity>
		<activity id="BLC_Test_Block0_Trial6_Trigger0_makeVisible_BLC_Test_Block0_Trial6_ContainerElements" ref="">
			<action delay="0.0" id="manipulateObject" repeat="1">
				<parameter name="visible" value="true"/>
				<parameter name="id" value="BLC_Test_Block0_Trial6_ContainerElement0"/>
			</action>
			<action delay="0.0" id="manipulateObject" repeat="1">
				<parameter name="visible" value="true"/>
				<parameter name="id" value="BLC_Test_Block0_Trial6_ContainerElement1"/>
			</action>
			<action delay="0.0" id="manipulateObject" repeat="1">
				<parameter name="visible" value="true"/>
				<parameter name="id" value="BLC_Test_Block0_Trial6_ContainerElement2"/>
			</action>
		</activity>
		<activity id="BLC_Test_Block0_Trial6_Trigger0_setupBrakeLaneChangeReactionTimer" ref="">
			<action delay="0.0" id="setupLaneChangeReactionTimer" repeat="1">
				<parameter name="minSteeringAngle" value="0"/>
				<parameter name="targetLane" value="1"/>
				<parameter name="startLane" value="2"/>
				<parameter name="taskCompletionAfterDistance" value="117"/>
				<parameter name="taskCompletionAfterTime" value="7000"/>
				<parameter name="timerID" value="timer1"/>
				<parameter name="allowBreak" value="true"/>
				<parameter name="successSound" value="good"/>
				<parameter name="congruenceClass" value="LaneChange"/>
				<parameter name="holdLaneFor" value="2000"/>
				<parameter name="failSound" value="fail"/>
			</action>
		</activity>
		<activity id="BLC_Test_Block0_Trial6_Trigger0_Sound_Stimulus" ref="">
			<action delay="0.0" id="playSound" repeat="1">
				<parameter name="soundID" value="right1"/>
			</action>
		</activity>
		<activity id="BLC_Test_Block0_Trial7_Trigger0_makeVisible_BLC_Test_Block0_Trial7_ContainerElements" ref="">
			<action delay="0.0" id="manipulateObject" repeat="1">
				<parameter name="visible" value="true"/>
				<parameter name="id" value="BLC_Test_Block0_Trial7_ContainerElement0"/>
			</action>
			<action delay="0.0" id="manipulateObject" repeat="1">
				<parameter name="visible" value="true"/>
				<parameter name="id" value="BLC_Test_Block0_Trial7_ContainerElement1"/>
			</action>
			<action delay="0.0" id="manipulateObject" repeat="1">
				<parameter name="visible" value="true"/>
				<parameter name="id" value="BLC_Test_Block0_Trial7_ContainerElement2"/>
			</action>
		</activity>
		<activity id="BLC_Test_Block0_Trial7_Trigger0_setupBrakeLaneChangeReactionTimer" ref="">
			<action delay="0.0" id="setupLaneChangeReactionTimer" repeat="1">
				<parameter name="minSteeringAngle" value="0"/>
				<parameter name="targetLane" value="2"/>
				<parameter name="startLane" value="1"/>
				<parameter name="taskCompletionAfterDistance" value="117"/>
				<parameter name="taskCompletionAfterTime" value="7000"/>
				<parameter name="timerID" value="timer1"/>
				<parameter name="allowBreak" value="true"/>
				<parameter name="successSound" value="good"/>
				<parameter name="congruenceClass" value="LaneChange"/>
				<parameter name="holdLaneFor" value="2000"/>
				<parameter name="failSound" value="fail"/>
			</action>
		</activity>
		<activity id="BLC_Test_Block0_Trial7_Trigger0_Sound_Stimulus" ref="">
			<action delay="0.0" id="playSound" repeat="1">
				<parameter name="soundID" value="left1"/>
			</action>
		</activity>
		<activity id="BLC_Test_Block0_Trial8_Trigger0_makeVisible_BLC_Test_Block0_Trial8_ContainerElements" ref="">
			<action delay="0.0" id="manipulateObject" repeat="1">
				<parameter name="visible" value="true"/>
				<parameter name="id" value="BLC_Test_Block0_Trial8_ContainerElement0"/>
			</action>
			<action delay="0.0" id="manipulateObject" repeat="1">
				<parameter name="visible" value="true"/>
				<parameter name="id" value="BLC_Test_Block0_Trial8_ContainerElement1"/>
			</action>
			<action delay="0.0" id="manipulateObject" repeat="1">
				<parameter name="visible" value="true"/>
				<parameter name="id" value="BLC_Test_Block0_Trial8_ContainerElement2"/>
			</action>
		</activity>
		<activity id="BLC_Test_Block0_Trial8_Trigger0_setupBrakeLaneChangeReactionTimer" ref="">
			<action delay="0.0" id="setupLaneChangeReactionTimer" repeat="1">
				<parameter name="minSteeringAngle" value="0"/>
				<parameter name="targetLane" value="0"/>
				<parameter name="startLane" value="2"/>
				<parameter name="taskCompletionAfterDistance" value="117"/>
				<parameter name="taskCompletionAfterTime" value="7000"/>
				<parameter name="timerID" value="timer1"/>
				<parameter name="allowBreak" value="true"/>
				<parameter name="successSound" value="good"/>
				<parameter name="congruenceClass" value="LaneChange"/>
				<parameter name="holdLaneFor" value="2000"/>
				<parameter name="failSound" value="fail"/>
			</action>
		</activity>
		<activity id="BLC_Test_Block0_Trial8_Trigger0_Sound_Stimulus" ref="">
			<action delay="0.0" id="playSound" repeat="1">
				<parameter name="soundID" value="right2"/>
			</action>
		</activity>
		<activity id="BLC_Test_Block0_Trial9_Trigger0_makeVisible_BLC_Test_Block0_Trial9_ContainerElements" ref="">
			<action delay="0.0" id="manipulateObject" repeat="1">
				<parameter name="visible" value="true"/>
				<parameter name="id" value="BLC_Test_Block0_Trial9_ContainerElement0"/>
			</action>
			<action delay="0.0" id="manipulateObject" repeat="1">
				<parameter name="visible" value="true"/>
				<parameter name="id" value="BLC_Test_Block0_Trial9_ContainerElement1"/>
			</action>
			<action delay="0.0" id="manipulateObject" repeat="1">
				<parameter name="visible" value="true"/>
				<parameter name="id" value="BLC_Test_Block0_Trial9_ContainerElement2"/>
			</action>
		</activity>
		<activity id="BLC_Test_Block0_Trial9_Trigger0_setupBrakeLaneChangeReactionTimer" ref="">
			<action delay="0.0" id="setupLaneChangeReactionTimer" repeat="1">
				<parameter name="minSteeringAngle" value="0"/>
				<parameter name="targetLane" value="2"/>
				<parameter name="startLane" value="0"/>
				<parameter name="taskCompletionAfterDistance" value="117"/>
				<parameter name="taskCompletionAfterTime" value="7000"/>
				<parameter name="timerID" value="timer1"/>
				<parameter name="allowBreak" value="true"/>
				<parameter name="successSound" value="good"/>
				<parameter name="congruenceClass" value="LaneChange"/>
				<parameter name="holdLaneFor" value="2000"/>
				<parameter name="failSound" value="fail"/>
			</action>
		</activity>
		<activity id="BLC_Test_Block0_Trial9_Trigger0_Sound_Stimulus" ref="">
			<action delay="0.0" id="playSound" repeat="1">
				<parameter name="soundID" value="left2"/>
			</action>
		</activity>
		<activity id="BLC_Test_Block0_Trial10_Trigger0_makeVisible_BLC_Test_Block0_Trial10_ContainerElements" ref="">
			<action delay="0.0" id="manipulateObject" repeat="1">
				<parameter name="visible" value="true"/>
				<parameter name="id" value="BLC_Test_Block0_Trial10_ContainerElement0"/>
			</action>
			<action delay="0.0" id="manipulateObject" repeat="1">
				<parameter name="visible" value="true"/>
				<parameter name="id" value="BLC_Test_Block0_Trial10_ContainerElement1"/>
			</action>
			<action delay="0.0" id="manipulateObject" repeat="1">
				<parameter name="visible" value="true"/>
				<parameter name="id" value="BLC_Test_Block0_Trial10_ContainerElement2"/>
			</action>
		</activity>
		<activity id="BLC_Test_Block0_Trial10_Trigger0_setupBrakeLaneChangeReactionTimer" ref="">
			<action delay="0.0" id="setupLaneChangeReactionTimer" repeat="1">
				<parameter name="minSteeringAngle" value="0"/>
				<parameter name="targetLane" value="0"/>
				<parameter name="startLane" value="2"/>
				<parameter name="taskCompletionAfterDistance" value="117"/>
				<parameter name="taskCompletionAfterTime" value="7000"/>
				<parameter name="timerID" value="timer1"/>
				<parameter name="allowBreak" value="true"/>
				<parameter name="successSound" value="good"/>
				<parameter name="congruenceClass" value="LaneChange"/>
				<parameter name="holdLaneFor" value="2000"/>
				<parameter name="failSound" value="fail"/>
			</action>
		</activity>
		<activity id="BLC_Test_Block0_Trial10_Trigger0_Sound_Stimulus" ref="">
			<action delay="0.0" id="playSound" repeat="1">
				<parameter name="soundID" value="right2"/>
			</action>
		</activity>
		<activity id="BLC_Test_Block0_Trial11_Trigger0_makeVisible_BLC_Test_Block0_Trial11_ContainerElements" ref="">
			<action delay="0.0" id="manipulateObject" repeat="1">
				<parameter name="visible" value="true"/>
				<parameter name="id" value="BLC_Test_Block0_Trial11_ContainerElement0"/>
			</action>
			<action delay="0.0" id="manipulateObject" repeat="1">
				<parameter name="visible" value="true"/>
				<parameter name="id" value="BLC_Test_Block0_Trial11_ContainerElement1"/>
			</action>
			<action delay="0.0" id="manipulateObject" repeat="1">
				<parameter name="visible" value="true"/>
				<parameter name="id" value="BLC_Test_Block0_Trial11_ContainerElement2"/>
			</action>
		</activity>
		<activity id="BLC_Test_Block0_Trial11_Trigger0_setupBrakeLaneChangeReactionTimer" ref="">
			<action delay="0.0" id="setupLaneChangeReactionTimer" repeat="1">
				<parameter name="minSteeringAngle" value="0"/>
				<parameter name="targetLane" value="1"/>
				<parameter name="startLane" value="0"/>
				<parameter name="taskCompletionAfterDistance" value="117"/>
				<parameter name="taskCompletionAfterTime" value="7000"/>
				<parameter name="timerID" value="timer1"/>
				<parameter name="allowBreak" value="true"/>
				<parameter name="successSound" value="good"/>
				<parameter name="congruenceClass" value="LaneChange"/>
				<parameter name="holdLaneFor" value="2000"/>
				<parameter name="failSound" value="fail"/>
			</action>
		</activity>
		<activity id="BLC_Test_Block0_Trial11_Trigger0_Sound_Stimulus" ref="">
			<action delay="0.0" id="playSound" repeat="1">
				<parameter name="soundID" value="left1"/>
			</action>
		</activity>
		<activity id="BLC_Test_Block0_Trial12_Trigger0_makeVisible_BLC_Test_Block0_Trial12_ContainerElements" ref="">
			<action delay="0.0" id="manipulateObject" repeat="1">
				<parameter name="visible" value="true"/>
				<parameter name="id" value="BLC_Test_Block0_Trial12_ContainerElement0"/>
			</action>
			<action delay="0.0" id="manipulateObject" repeat="1">
				<parameter name="visible" value="true"/>
				<parameter name="id" value="BLC_Test_Block0_Trial12_ContainerElement1"/>
			</action>
			<action delay="0.0" id="manipulateObject" repeat="1">
				<parameter name="visible" value="true"/>
				<parameter name="id" value="BLC_Test_Block0_Trial12_ContainerElement2"/>
			</action>
		</activity>
		<activity id="BLC_Test_Block0_Trial12_Trigger0_setupBrakeLaneChangeReactionTimer" ref="">
			<action delay="0.0" id="setupLaneChangeReactionTimer" repeat="1">
				<parameter name="minSteeringAngle" value="0"/>
				<parameter name="targetLane" value="2"/>
				<parameter name="startLane" value="1"/>
				<parameter name="taskCompletionAfterDistance" value="117"/>
				<parameter name="taskCompletionAfterTime" value="7000"/>
				<parameter name="timerID" value="timer1"/>
				<parameter name="allowBreak" value="true"/>
				<parameter name="successSound" value="good"/>
				<parameter name="congruenceClass" value="LaneChange"/>
				<parameter name="holdLaneFor" value="2000"/>
				<parameter name="failSound" value="fail"/>
			</action>
		</activity>
		<activity id="BLC_Test_Block0_Trial12_Trigger0_Sound_Stimulus" ref="">
			<action delay="0.0" id="playSound" repeat="1">
				<parameter name="soundID" value="left1"/>
			</action>
		</activity>
		<activity id="BLC_Test_Block0_Trial13_Trigger0_makeVisible_BLC_Test_Block0_Trial13_ContainerElements" ref="">
			<action delay="0.0" id="manipulateObject" repeat="1">
				<parameter name="visible" value="true"/>
				<parameter name="id" value="BLC_Test_Block0_Trial13_ContainerElement0"/>
			</action>
			<action delay="0.0" id="manipulateObject" repeat="1">
				<parameter name="visible" value="true"/>
				<parameter name="id" value="BLC_Test_Block0_Trial13_ContainerElement1"/>
			</action>
			<action delay="0.0" id="manipulateObject" repeat="1">
				<parameter name="visible" value="true"/>
				<parameter name="id" value="BLC_Test_Block0_Trial13_ContainerElement2"/>
			</action>
		</activity>
		<activity id="BLC_Test_Block0_Trial13_Trigger0_setupBrakeLaneChangeReactionTimer" ref="">
			<action delay="0.0" id="setupLaneChangeReactionTimer" repeat="1">
				<parameter name="minSteeringAngle" value="0"/>
				<parameter name="targetLane" value="1"/>
				<parameter name="startLane" value="2"/>
				<parameter name="taskCompletionAfterDistance" value="117"/>
				<parameter name="taskCompletionAfterTime" value="7000"/>
				<parameter name="timerID" value="timer1"/>
				<parameter name="allowBreak" value="true"/>
				<parameter name="successSound" value="good"/>
				<parameter name="congruenceClass" value="LaneChange"/>
				<parameter name="holdLaneFor" value="2000"/>
				<parameter name="failSound" value="fail"/>
			</action>
		</activity>
		<activity id="BLC_Test_Block0_Trial13_Trigger0_Sound_Stimulus" ref="">
			<action delay="0.0" id="playSound" repeat="1">
				<parameter name="soundID" value="right1"/>
			</action>
		</activity>
		<activity id="BLC_Test_Block0_Trial14_Trigger0_makeVisible_BLC_Test_Block0_Trial14_ContainerElements" ref="">
			<action delay="0.0" id="manipulateObject" repeat="1">
				<parameter name="visible" value="true"/>
				<parameter name="id" value="BLC_Test_Block0_Trial14_ContainerElement0"/>
			</action>
			<action delay="0.0" id="manipulateObject" repeat="1">
				<parameter name="visible" value="true"/>
				<parameter name="id" value="BLC_Test_Block0_Trial14_ContainerElement1"/>
			</action>
			<action delay="0.0" id="manipulateObject" repeat="1">
				<parameter name="visible" value="true"/>
				<parameter name="id" value="BLC_Test_Block0_Trial14_ContainerElement2"/>
			</action>
		</activity>
		<activity id="BLC_Test_Block0_Trial14_Trigger0_setupBrakeLaneChangeReactionTimer" ref="">
			<action delay="0.0" id="setupLaneChangeReactionTimer" repeat="1">
				<parameter name="minSteeringAngle" value="0"/>
				<parameter name="targetLane" value="0"/>
				<parameter name="startLane" value="1"/>
				<parameter name="taskCompletionAfterDistance" value="117"/>
				<parameter name="taskCompletionAfterTime" value="7000"/>
				<parameter name="timerID" value="timer1"/>
				<parameter name="allowBreak" value="true"/>
				<parameter name="successSound" value="good"/>
				<parameter name="congruenceClass" value="LaneChange"/>
				<parameter name="holdLaneFor" value="2000"/>
				<parameter name="failSound" value="fail"/>
			</action>
		</activity>
		<activity id="BLC_Test_Block0_Trial14_Trigger0_Sound_Stimulus" ref="">
			<action delay="0.0" id="playSound" repeat="1">
				<parameter name="soundID" value="right1"/>
			</action>
		</activity>
		<activity id="BLC_Test_Block0_Trial15_Trigger0_makeVisible_BLC_Test_Block0_Trial15_ContainerElements" ref="">
			<action delay="0.0" id="manipulateObject" repeat="1">
				<parameter name="visible" value="true"/>
				<parameter name="id" value="BLC_Test_Block0_Trial15_ContainerElement0"/>
			</action>
			<action delay="0.0" id="manipulateObject" repeat="1">
				<parameter name="visible" value="true"/>
				<parameter name="id" value="BLC_Test_Block0_Trial15_ContainerElement1"/>
			</action>
			<action delay="0.0" id="manipulateObject" repeat="1">
				<parameter name="visible" value="true"/>
				<parameter name="id" value="BLC_Test_Block0_Trial15_ContainerElement2"/>
			</action>
		</activity>
		<activity id="BLC_Test_Block0_Trial15_Trigger0_setupBrakeLaneChangeReactionTimer" ref="">
			<action delay="0.0" id="setupLaneChangeReactionTimer" repeat="1">
				<parameter name="minSteeringAngle" value="0"/>
				<parameter name="targetLane" value="1"/>
				<parameter name="startLane" value="0"/>
				<parameter name="taskCompletionAfterDistance" value="117"/>
				<parameter name="taskCompletionAfterTime" value="7000"/>
				<parameter name="timerID" value="timer1"/>
				<parameter name="allowBreak" value="true"/>
				<parameter name="successSound" value="good"/>
				<parameter name="congruenceClass" value="LaneChange"/>
				<parameter name="holdLaneFor" value="2000"/>
				<parameter name="failSound" value="fail"/>
			</action>
		</activity>
		<activity id="BLC_Test_Block0_Trial15_Trigger0_Sound_Stimulus" ref="">
			<action delay="0.0" id="playSound" repeat="1">
				<parameter name="soundID" value="left1"/>
			</action>
		</activity>
		<activity id="BLC_Test_Block0_Trial16_Trigger0_makeVisible_BLC_Test_Block0_Trial16_ContainerElements" ref="">
			<action delay="0.0" id="manipulateObject" repeat="1">
				<parameter name="visible" value="true"/>
				<parameter name="id" value="BLC_Test_Block0_Trial16_ContainerElement0"/>
			</action>
			<action delay="0.0" id="manipulateObject" repeat="1">
				<parameter name="visible" value="true"/>
				<parameter name="id" value="BLC_Test_Block0_Trial16_ContainerElement1"/>
			</action>
			<action delay="0.0" id="manipulateObject" repeat="1">
				<parameter name="visible" value="true"/>
				<parameter name="id" value="BLC_Test_Block0_Trial16_ContainerElement2"/>
			</action>
		</activity>
		<activity id="BLC_Test_Block0_Trial16_Trigger0_setupBrakeLaneChangeReactionTimer" ref="">
			<action delay="0.0" id="setupLaneChangeReactionTimer" repeat="1">
				<parameter name="minSteeringAngle" value="0"/>
				<parameter name="targetLane" value="0"/>
				<parameter name="startLane" value="1"/>
				<parameter name="taskCompletionAfterDistance" value="117"/>
				<parameter name="taskCompletionAfterTime" value="7000"/>
				<parameter name="timerID" value="timer1"/>
				<parameter name="allowBreak" value="true"/>
				<parameter name="successSound" value="good"/>
				<parameter name="congruenceClass" value="LaneChange"/>
				<parameter name="holdLaneFor" value="2000"/>
				<parameter name="failSound" value="fail"/>
			</action>
		</activity>
		<activity id="BLC_Test_Block0_Trial16_Trigger0_Sound_Stimulus" ref="">
			<action delay="0.0" id="playSound" repeat="1">
				<parameter name="soundID" value="right1"/>
			</action>
		</activity>
		<activity id="BLC_Test_Block0_Trial17_Trigger0_makeVisible_BLC_Test_Block0_Trial17_ContainerElements" ref="">
			<action delay="0.0" id="manipulateObject" repeat="1">
				<parameter name="visible" value="true"/>
				<parameter name="id" value="BLC_Test_Block0_Trial17_ContainerElement0"/>
			</action>
			<action delay="0.0" id="manipulateObject" repeat="1">
				<parameter name="visible" value="true"/>
				<parameter name="id" value="BLC_Test_Block0_Trial17_ContainerElement1"/>
			</action>
			<action delay="0.0" id="manipulateObject" repeat="1">
				<parameter name="visible" value="true"/>
				<parameter name="id" value="BLC_Test_Block0_Trial17_ContainerElement2"/>
			</action>
		</activity>
		<activity id="BLC_Test_Block0_Trial17_Trigger0_setupBrakeLaneChangeReactionTimer" ref="">
			<action delay="0.0" id="setupLaneChangeReactionTimer" repeat="1">
				<parameter name="minSteeringAngle" value="0"/>
				<parameter name="targetLane" value="1"/>
				<parameter name="startLane" value="0"/>
				<parameter name="taskCompletionAfterDistance" value="117"/>
				<parameter name="taskCompletionAfterTime" value="7000"/>
				<parameter name="timerID" value="timer1"/>
				<parameter name="allowBreak" value="true"/>
				<parameter name="successSound" value="good"/>
				<parameter name="congruenceClass" value="LaneChange"/>
				<parameter name="holdLaneFor" value="2000"/>
				<parameter name="failSound" value="fail"/>
			</action>
		</activity>
		<activity id="BLC_Test_Block0_Trial17_Trigger0_Sound_Stimulus" ref="">
			<action delay="0.0" id="playSound" repeat="1">
				<parameter name="soundID" value="left1"/>
			</action>
		</activity>
	</activities>
	<triggers>
		<trigger id="BLC_Test_Start_Trigger" priority="1">
			<activities>
				<activity ref="Start_startRM"/>
				<activity ref="Start_startRecording"/>
			</activities>
			<condition>collideWith:BLC_Test_Start_Trigger</condition>
		</trigger>
		<trigger id="BLC_Test_End_Trigger" priority="1">
			<activities>
				<activity ref="End_stopRecording"/>
				<activity ref="End_pauseSimulation"/>
			</activities>
			<condition>collideWith:BLC_Test_End_Trigger</condition>
		</trigger>
			<trigger id="BLC_Test_Block0_Trial0_Trigger0" priority="1">
				<activities>
					<activity ref="BLC_Test_Block0_Trial0_Trigger0_makeVisible_BLC_Test_Block0_Trial0_ContainerElements"/>
					<activity ref="BLC_Test_Block0_Trial0_Trigger0_setupBrakeLaneChangeReactionTimer"/>
				</activities>
				<condition>collideWith:BLC_Test_Block0_Trial0_Trigger0</condition>
			</trigger>
			<trigger id="BLC_Test_Block0_Trial0_Stimulus_Trigger0" priority="1">
				<activities>
					<activity ref="BLC_Test_Block0_Trial0_Trigger0_Sound_Stimulus"/>
				</activities>
				<condition>collideWith:BLC_Test_Block0_Trial0_Stimulus_Trigger0</condition>
			</trigger>
			<trigger id="BLC_Test_Block0_Trial1_Trigger0" priority="1">
				<activities>
					<activity ref="BLC_Test_Block0_Trial1_Trigger0_makeVisible_BLC_Test_Block0_Trial1_ContainerElements"/>
					<activity ref="BLC_Test_Block0_Trial1_Trigger0_setupBrakeLaneChangeReactionTimer"/>
				</activities>
				<condition>collideWith:BLC_Test_Block0_Trial1_Trigger0</condition>
			</trigger>
			<trigger id="BLC_Test_Block0_Trial1_Stimulus_Trigger0" priority="1">
				<activities>
					<activity ref="BLC_Test_Block0_Trial1_Trigger0_Sound_Stimulus"/>
				</activities>
				<condition>collideWith:BLC_Test_Block0_Trial1_Stimulus_Trigger0</condition>
			</trigger>
			<trigger id="BLC_Test_Block0_Trial2_Trigger0" priority="1">
				<activities>
					<activity ref="BLC_Test_Block0_Trial2_Trigger0_makeVisible_BLC_Test_Block0_Trial2_ContainerElements"/>
					<activity ref="BLC_Test_Block0_Trial2_Trigger0_setupBrakeLaneChangeReactionTimer"/>
				</activities>
				<condition>collideWith:BLC_Test_Block0_Trial2_Trigger0</condition>
			</trigger>
			<trigger id="BLC_Test_Block0_Trial2_Stimulus_Trigger0" priority="1">
				<activities>
					<activity ref="BLC_Test_Block0_Trial2_Trigger0_Sound_Stimulus"/>
				</activities>
				<condition>collideWith:BLC_Test_Block0_Trial2_Stimulus_Trigger0</condition>
			</trigger>
			<trigger id="BLC_Test_Block0_Trial3_Trigger0" priority="1">
				<activities>
					<activity ref="BLC_Test_Block0_Trial3_Trigger0_makeVisible_BLC_Test_Block0_Trial3_ContainerElements"/>
					<activity ref="BLC_Test_Block0_Trial3_Trigger0_setupBrakeLaneChangeReactionTimer"/>
				</activities>
				<condition>collideWith:BLC_Test_Block0_Trial3_Trigger0</condition>
			</trigger>
			<trigger id="BLC_Test_Block0_Trial3_Stimulus_Trigger0" priority="1">
				<activities>
					<activity ref="BLC_Test_Block0_Trial3_Trigger0_Sound_Stimulus"/>
				</activities>
				<condition>collideWith:BLC_Test_Block0_Trial3_Stimulus_Trigger0</condition>
			</trigger>
			<trigger id="BLC_Test_Block0_Trial4_Trigger0" priority="1">
				<activities>
					<activity ref="BLC_Test_Block0_Trial4_Trigger0_makeVisible_BLC_Test_Block0_Trial4_ContainerElements"/>
					<activity ref="BLC_Test_Block0_Trial4_Trigger0_setupBrakeLaneChangeReactionTimer"/>
				</activities>
				<condition>collideWith:BLC_Test_Block0_Trial4_Trigger0</condition>
			</trigger>
			<trigger id="BLC_Test_Block0_Trial4_Stimulus_Trigger0" priority="1">
				<activities>
					<activity ref="BLC_Test_Block0_Trial4_Trigger0_Sound_Stimulus"/>
				</activities>
				<condition>collideWith:BLC_Test_Block0_Trial4_Stimulus_Trigger0</condition>
			</trigger>
			<trigger id="BLC_Test_Block0_Trial5_Trigger0" priority="1">
				<activities>
					<activity ref="BLC_Test_Block0_Trial5_Trigger0_makeVisible_BLC_Test_Block0_Trial5_ContainerElements"/>
					<activity ref="BLC_Test_Block0_Trial5_Trigger0_setupBrakeLaneChangeReactionTimer"/>
				</activities>
				<condition>collideWith:BLC_Test_Block0_Trial5_Trigger0</condition>
			</trigger>
			<trigger id="BLC_Test_Block0_Trial5_Stimulus_Trigger0" priority="1">
				<activities>
					<activity ref="BLC_Test_Block0_Trial5_Trigger0_Sound_Stimulus"/>
				</activities>
				<condition>collideWith:BLC_Test_Block0_Trial5_Stimulus_Trigger0</condition>
			</trigger>
			<trigger id="BLC_Test_Block0_Trial6_Trigger0" priority="1">
				<activities>
					<activity ref="BLC_Test_Block0_Trial6_Trigger0_makeVisible_BLC_Test_Block0_Trial6_ContainerElements"/>
					<activity ref="BLC_Test_Block0_Trial6_Trigger0_setupBrakeLaneChangeReactionTimer"/>
				</activities>
				<condition>collideWith:BLC_Test_Block0_Trial6_Trigger0</condition>
			</trigger>
			<trigger id="BLC_Test_Block0_Trial6_Stimulus_Trigger0" priority="1">
				<activities>
					<activity ref="BLC_Test_Block0_Trial6_Trigger0_Sound_Stimulus"/>
				</activities>
				<condition>collideWith:BLC_Test_Block0_Trial6_Stimulus_Trigger0</condition>
			</trigger>
			<trigger id="BLC_Test_Block0_Trial7_Trigger0" priority="1">
				<activities>
					<activity ref="BLC_Test_Block0_Trial7_Trigger0_makeVisible_BLC_Test_Block0_Trial7_ContainerElements"/>
					<activity ref="BLC_Test_Block0_Trial7_Trigger0_setupBrakeLaneChangeReactionTimer"/>
				</activities>
				<condition>collideWith:BLC_Test_Block0_Trial7_Trigger0</condition>
			</trigger>
			<trigger id="BLC_Test_Block0_Trial7_Stimulus_Trigger0" priority="1">
				<activities>
					<activity ref="BLC_Test_Block0_Trial7_Trigger0_Sound_Stimulus"/>
				</activities>
				<condition>collideWith:BLC_Test_Block0_Trial7_Stimulus_Trigger0</condition>
			</trigger>
			<trigger id="BLC_Test_Block0_Trial8_Trigger0" priority="1">
				<activities>
					<activity ref="BLC_Test_Block0_Trial8_Trigger0_makeVisible_BLC_Test_Block0_Trial8_ContainerElements"/>
					<activity ref="BLC_Test_Block0_Trial8_Trigger0_setupBrakeLaneChangeReactionTimer"/>
				</activities>
				<condition>collideWith:BLC_Test_Block0_Trial8_Trigger0</condition>
			</trigger>
			<trigger id="BLC_Test_Block0_Trial8_Stimulus_Trigger0" priority="1">
				<activities>
					<activity ref="BLC_Test_Block0_Trial8_Trigger0_Sound_Stimulus"/>
				</activities>
				<condition>collideWith:BLC_Test_Block0_Trial8_Stimulus_Trigger0</condition>
			</trigger>
			<trigger id="BLC_Test_Block0_Trial9_Trigger0" priority="1">
				<activities>
					<activity ref="BLC_Test_Block0_Trial9_Trigger0_makeVisible_BLC_Test_Block0_Trial9_ContainerElements"/>
					<activity ref="BLC_Test_Block0_Trial9_Trigger0_setupBrakeLaneChangeReactionTimer"/>
				</activities>
				<condition>collideWith:BLC_Test_Block0_Trial9_Trigger0</condition>
			</trigger>
			<trigger id="BLC_Test_Block0_Trial9_Stimulus_Trigger0" priority="1">
				<activities>
					<activity ref="BLC_Test_Block0_Trial9_Trigger0_Sound_Stimulus"/>
				</activities>
				<condition>collideWith:BLC_Test_Block0_Trial9_Stimulus_Trigger0</condition>
			</trigger>
			<trigger id="BLC_Test_Block0_Trial10_Trigger0" priority="1">
				<activities>
					<activity ref="BLC_Test_Block0_Trial10_Trigger0_makeVisible_BLC_Test_Block0_Trial10_ContainerElements"/>
					<activity ref="BLC_Test_Block0_Trial10_Trigger0_setupBrakeLaneChangeReactionTimer"/>
				</activities>
				<condition>collideWith:BLC_Test_Block0_Trial10_Trigger0</condition>
			</trigger>
			<trigger id="BLC_Test_Block0_Trial10_Stimulus_Trigger0" priority="1">
				<activities>
					<activity ref="BLC_Test_Block0_Trial10_Trigger0_Sound_Stimulus"/>
				</activities>
				<condition>collideWith:BLC_Test_Block0_Trial10_Stimulus_Trigger0</condition>
			</trigger>
			<trigger id="BLC_Test_Block0_Trial11_Trigger0" priority="1">
				<activities>
					<activity ref="BLC_Test_Block0_Trial11_Trigger0_makeVisible_BLC_Test_Block0_Trial11_ContainerElements"/>
					<activity ref="BLC_Test_Block0_Trial11_Trigger0_setupBrakeLaneChangeReactionTimer"/>
				</activities>
				<condition>collideWith:BLC_Test_Block0_Trial11_Trigger0</condition>
			</trigger>
			<trigger id="BLC_Test_Block0_Trial11_Stimulus_Trigger0" priority="1">
				<activities>
					<activity ref="BLC_Test_Block0_Trial11_Trigger0_Sound_Stimulus"/>
				</activities>
				<condition>collideWith:BLC_Test_Block0_Trial11_Stimulus_Trigger0</condition>
			</trigger>
			<trigger id="BLC_Test_Block0_Trial12_Trigger0" priority="1">
				<activities>
					<activity ref="BLC_Test_Block0_Trial12_Trigger0_makeVisible_BLC_Test_Block0_Trial12_ContainerElements"/>
					<activity ref="BLC_Test_Block0_Trial12_Trigger0_setupBrakeLaneChangeReactionTimer"/>
				</activities>
				<condition>collideWith:BLC_Test_Block0_Trial12_Trigger0</condition>
			</trigger>
			<trigger id="BLC_Test_Block0_Trial12_Stimulus_Trigger0" priority="1">
				<activities>
					<activity ref="BLC_Test_Block0_Trial12_Trigger0_Sound_Stimulus"/>
				</activities>
				<condition>collideWith:BLC_Test_Block0_Trial12_Stimulus_Trigger0</condition>
			</trigger>
			<trigger id="BLC_Test_Block0_Trial13_Trigger0" priority="1">
				<activities>
					<activity ref="BLC_Test_Block0_Trial13_Trigger0_makeVisible_BLC_Test_Block0_Trial13_ContainerElements"/>
					<activity ref="BLC_Test_Block0_Trial13_Trigger0_setupBrakeLaneChangeReactionTimer"/>
				</activities>
				<condition>collideWith:BLC_Test_Block0_Trial13_Trigger0</condition>
			</trigger>
			<trigger id="BLC_Test_Block0_Trial13_Stimulus_Trigger0" priority="1">
				<activities>
					<activity ref="BLC_Test_Block0_Trial13_Trigger0_Sound_Stimulus"/>
				</activities>
				<condition>collideWith:BLC_Test_Block0_Trial13_Stimulus_Trigger0</condition>
			</trigger>
			<trigger id="BLC_Test_Block0_Trial14_Trigger0" priority="1">
				<activities>
					<activity ref="BLC_Test_Block0_Trial14_Trigger0_makeVisible_BLC_Test_Block0_Trial14_ContainerElements"/>
					<activity ref="BLC_Test_Block0_Trial14_Trigger0_setupBrakeLaneChangeReactionTimer"/>
				</activities>
				<condition>collideWith:BLC_Test_Block0_Trial14_Trigger0</condition>
			</trigger>
			<trigger id="BLC_Test_Block0_Trial14_Stimulus_Trigger0" priority="1">
				<activities>
					<activity ref="BLC_Test_Block0_Trial14_Trigger0_Sound_Stimulus"/>
				</activities>
				<condition>collideWith:BLC_Test_Block0_Trial14_Stimulus_Trigger0</condition>
			</trigger>
			<trigger id="BLC_Test_Block0_Trial15_Trigger0" priority="1">
				<activities>
					<activity ref="BLC_Test_Block0_Trial15_Trigger0_makeVisible_BLC_Test_Block0_Trial15_ContainerElements"/>
					<activity ref="BLC_Test_Block0_Trial15_Trigger0_setupBrakeLaneChangeReactionTimer"/>
				</activities>
				<condition>collideWith:BLC_Test_Block0_Trial15_Trigger0</condition>
			</trigger>
			<trigger id="BLC_Test_Block0_Trial15_Stimulus_Trigger0" priority="1">
				<activities>
					<activity ref="BLC_Test_Block0_Trial15_Trigger0_Sound_Stimulus"/>
				</activities>
				<condition>collideWith:BLC_Test_Block0_Trial15_Stimulus_Trigger0</condition>
			</trigger>
			<trigger id="BLC_Test_Block0_Trial16_Trigger0" priority="1">
				<activities>
					<activity ref="BLC_Test_Block0_Trial16_Trigger0_makeVisible_BLC_Test_Block0_Trial16_ContainerElements"/>
					<activity ref="BLC_Test_Block0_Trial16_Trigger0_setupBrakeLaneChangeReactionTimer"/>
				</activities>
				<condition>collideWith:BLC_Test_Block0_Trial16_Trigger0</condition>
			</trigger>
			<trigger id="BLC_Test_Block0_Trial16_Stimulus_Trigger0" priority="1">
				<activities>
					<activity ref="BLC_Test_Block0_Trial16_Trigger0_Sound_Stimulus"/>
				</activities>
				<condition>collideWith:BLC_Test_Block0_Trial16_Stimulus_Trigger0</condition>
			</trigger>
			<trigger id="BLC_Test_Block0_Trial17_Trigger0" priority="1">
				<activities>
					<activity ref="BLC_Test_Block0_Trial17_Trigger0_makeVisible_BLC_Test_Block0_Trial17_ContainerElements"/>
					<activity ref="BLC_Test_Block0_Trial17_Trigger0_setupBrakeLaneChangeReactionTimer"/>
				</activities>
				<condition>collideWith:BLC_Test_Block0_Trial17_Trigger0</condition>
			</trigger>
			<trigger id="BLC_Test_Block0_Trial17_Stimulus_Trigger0" priority="1">
				<activities>
					<activity ref="BLC_Test_Block0_Trial17_Trigger0_Sound_Stimulus"/>
				</activities>
				<condition>collideWith:BLC_Test_Block0_Trial17_Stimulus_Trigger0</condition>
			</trigger>
	</triggers>
</interaction>
